recall_db/__init__.py
recalldb-0.1.0.dist-info/licenses/LICENSE
recalldb-0.1.0.dist-info/METADATA
recalldb-0.1.0.dist-info/WHEEL
recalldb-0.1.0.dist-info/top_level.txt
recalldb-0.1.0.dist-info/RECORD
