Metadata-Version: 2.4
Name: recalldb
Version: 0.1.0
Summary: A multi-user vector database for efficient document storage and retrieval
Home-page: https://github.com/yourusername/recalldb
Author: RecallDB Team
Author-email: RecallDB Team <info@recalldb.ai>
License: MIT
Project-URL: Homepage, https://github.com/yourusername/recalldb
Project-URL: Bug Tracker, https://github.com/yourusername/recalldb/issues
Keywords: vector database,embeddings,search,rag,ai
Classifier: Programming Language :: Python :: 3
Classifier: License :: OSI Approved :: MIT License
Classifier: Operating System :: OS Independent
Classifier: Topic :: Database
Classifier: Topic :: Scientific/Engineering :: Artificial Intelligence
Requires-Python: >=3.8
License-File: LICENSE
Requires-Dist: numpy<2.0.0,>=1.20.0
Requires-Dist: pandas>=1.3.0
Requires-Dist: pyarrow>=7.0.0
Requires-Dist: scikit-learn>=1.0.0
Dynamic: author
Dynamic: home-page
Dynamic: license-file
Dynamic: requires-python
